voicerestore/__init__.py
voicerestore/env.py
voicerestore/model.py
voicerestore/restore.py
voicerestore/tensor_typing.py
voicerestore/utils.py
voicerestore/voice_restore.py
voicerestore/bigvgan/LICENSE.BigVGAN
voicerestore/bigvgan/__init__.py
voicerestore/bigvgan/activations.py
voicerestore/bigvgan/bigvgan.py
voicerestore/bigvgan/meldataset.py
voicerestore/bigvgan/alias_free_activation/cuda/__init__.py
voicerestore/bigvgan/alias_free_activation/cuda/activation1d.py
voicerestore/bigvgan/alias_free_activation/cuda/anti_alias_activation.cpp
voicerestore/bigvgan/alias_free_activation/cuda/anti_alias_activation_cuda.cu
voicerestore/bigvgan/alias_free_activation/cuda/compat.h
voicerestore/bigvgan/alias_free_activation/cuda/load.py
voicerestore/bigvgan/alias_free_activation/cuda/type_shim.h
voicerestore/bigvgan/alias_free_activation/torch/__init__.py
voicerestore/bigvgan/alias_free_activation/torch/act.py
voicerestore/bigvgan/alias_free_activation/torch/filter.py
voicerestore/bigvgan/alias_free_activation/torch/resample.py
voicerestore-0.1.1.dist-info/METADATA
voicerestore-0.1.1.dist-info/WHEEL
voicerestore-0.1.1.dist-info/RECORD
