Metadata-Version: 2.4
Name: voicerestore
Version: 0.1.1
Summary: Voice restoration using BigVGAN
Project-URL: Homepage, https://github.com/MiniXC/voicerestore-pip
Project-URL: Repository, https://github.com/MiniXC/voicerestore-pip.git
Author-email: Christoph Minixhofer <christoph.minixhofer@gmail.com>
License-Expression: MIT
Classifier: License :: OSI Approved :: MIT License
Classifier: Operating System :: OS Independent
Classifier: Programming Language :: Python :: 3
Requires-Python: >=3.8
Requires-Dist: einops
Requires-Dist: gateloop-transformer>=0.2.5
Requires-Dist: gdown
Requires-Dist: huggingface-hub>=0.24.6
Requires-Dist: jaxtyping>=0.2.34
Requires-Dist: librosa
Requires-Dist: matplotlib>=3.9.2
Requires-Dist: ninja
Requires-Dist: pyyaml
Requires-Dist: rotary-embedding-torch>=0.8.3
Requires-Dist: scikit-learn>=1.5.1
Requires-Dist: scipy>=1.14.1
Requires-Dist: soundfile>=0.12.1
Requires-Dist: torch>=2.4.1
Requires-Dist: torchaudio>=2.4.1
Requires-Dist: torchdiffeq>=0.2.4
Requires-Dist: torchvision>=0.19.1
Requires-Dist: tqdm>=4.66.5
Requires-Dist: x-transformers>=1.34.0
Provides-Extra: test
Requires-Dist: pytest-cov>=4.0.0; extra == 'test'
Requires-Dist: pytest>=7.0.0; extra == 'test'
